<?xml version="1.0" encoding="UTF-8"?>
<!DOCTYPE mapper PUBLIC "-//mybatis.org//DTD Mapper 3.0//EN" "http://mybatis.org/dtd/mybatis-3-mapper.dtd">
<mapper namespace="com.hdsoft.coremailbridge.persistence.UserMapper">
  <resultMap id="BaseResultMap" type="com.hdsoft.model.User">
    <!--
      WARNING - @mbggenerated
      This element is automatically generated by MyBatis Generator, do not modify.
      This element was generated on Sat Jan 19 09:51:17 CST 2019.
    -->
    <id column="id" jdbcType="BIGINT" property="id" />
    <result column="user_name" jdbcType="VARCHAR" property="userName" />
    <result column="display_name" jdbcType="VARCHAR" property="displayName" />
    <result column="password" jdbcType="VARCHAR" property="password" />
    <result column="department_code" jdbcType="VARCHAR" property="departmentCode" />
    <result column="nim_account" jdbcType="VARCHAR" property="nimAccount" />
    <result column="nim_token" jdbcType="VARCHAR" property="nimToken" />
    <result column="qs_account" jdbcType="VARCHAR" property="qsAccount" />
    <result column="create_time" jdbcType="TIMESTAMP" property="createTime" />
    <result column="update_time" jdbcType="TIMESTAMP" property="updateTime" />
  </resultMap>
  <sql id="Example_Where_Clause">
    <!--
      WARNING - @mbggenerated
      This element is automatically generated by MyBatis Generator, do not modify.
      This element was generated on Sat Jan 19 09:51:17 CST 2019.
    -->
    <where>
      <foreach collection="oredCriteria" item="criteria" separator="or">
        <if test="criteria.valid">
          <trim prefix="(" prefixOverrides="and" suffix=")">
            <foreach collection="criteria.criteria" item="criterion">
              <choose>
                <when test="criterion.noValue">
                  and ${criterion.condition}
                </when>
                <when test="criterion.singleValue">
                  and ${criterion.condition} #{criterion.value}
                </when>
                <when test="criterion.betweenValue">
                  and ${criterion.condition} #{criterion.value} and #{criterion.secondValue}
                </when>
                <when test="criterion.listValue">
                  and ${criterion.condition}
                  <foreach close=")" collection="criterion.value" item="listItem" open="(" separator=",">
                    #{listItem}
                  </foreach>
                </when>
              </choose>
            </foreach>
          </trim>
        </if>
      </foreach>
    </where>
  </sql>
  <sql id="Update_By_Example_Where_Clause">
    <!--
      WARNING - @mbggenerated
      This element is automatically generated by MyBatis Generator, do not modify.
      This element was generated on Sat Jan 19 09:51:17 CST 2019.
    -->
    <where>
      <foreach collection="example.oredCriteria" item="criteria" separator="or">
        <if test="criteria.valid">
          <trim prefix="(" prefixOverrides="and" suffix=")">
            <foreach collection="criteria.criteria" item="criterion">
              <choose>
                <when test="criterion.noValue">
                  and ${criterion.condition}
                </when>
                <when test="criterion.singleValue">
                  and ${criterion.condition} #{criterion.value}
                </when>
                <when test="criterion.betweenValue">
                  and ${criterion.condition} #{criterion.value} and #{criterion.secondValue}
                </when>
                <when test="criterion.listValue">
                  and ${criterion.condition}
                  <foreach close=")" collection="criterion.value" item="listItem" open="(" separator=",">
                    #{listItem}
                  </foreach>
                </when>
              </choose>
            </foreach>
          </trim>
        </if>
      </foreach>
    </where>
  </sql>
  <sql id="Base_Column_List">
    <!--
      WARNING - @mbggenerated
      This element is automatically generated by MyBatis Generator, do not modify.
      This element was generated on Sat Jan 19 09:51:17 CST 2019.
    -->
    id, user_name, display_name, password, department_code, nim_account, nim_token, qs_account,
    create_time, update_time
  </sql>
  <select id="selectByExample" parameterType="com.hdsoft.model.UserExample" resultMap="BaseResultMap">
    <!--
      WARNING - @mbggenerated
      This element is automatically generated by MyBatis Generator, do not modify.
      This element was generated on Sat Jan 19 09:51:17 CST 2019.
    -->
    select
    <if test="distinct">
      distinct
    </if>
    <include refid="Base_Column_List" />
    from coremailbridge_user
    <if test="_parameter != null">
      <include refid="Example_Where_Clause" />
    </if>
    <if test="orderByClause != null">
      order by ${orderByClause}
    </if>
  </select>
  <select id="selectByPrimaryKey" parameterType="java.lang.Long" resultMap="BaseResultMap">
    <!--
      WARNING - @mbggenerated
      This element is automatically generated by MyBatis Generator, do not modify.
      This element was generated on Sat Jan 19 09:51:17 CST 2019.
    -->
    select
    <include refid="Base_Column_List" />
    from coremailbridge_user
    where id = #{id,jdbcType=BIGINT}
  </select>
  <delete id="deleteByPrimaryKey" parameterType="java.lang.Long">
    <!--
      WARNING - @mbggenerated
      This element is automatically generated by MyBatis Generator, do not modify.
      This element was generated on Sat Jan 19 09:51:17 CST 2019.
    -->
    delete from coremailbridge_user
    where id = #{id,jdbcType=BIGINT}
  </delete>
  <delete id="deleteByExample" parameterType="com.hdsoft.model.UserExample">
    <!--
      WARNING - @mbggenerated
      This element is automatically generated by MyBatis Generator, do not modify.
      This element was generated on Sat Jan 19 09:51:17 CST 2019.
    -->
    delete from coremailbridge_user
    <if test="_parameter != null">
      <include refid="Example_Where_Clause" />
    </if>
  </delete>
  <insert id="insert" parameterType="com.hdsoft.model.User">
    <!--
      WARNING - @mbggenerated
      This element is automatically generated by MyBatis Generator, do not modify.
      This element was generated on Sat Jan 19 09:51:17 CST 2019.
    -->
    insert into coremailbridge_user (id, user_name, display_name,
      password, department_code, nim_account,
      nim_token, qs_account, create_time,
      update_time)
    values (#{id,jdbcType=BIGINT}, #{userName,jdbcType=VARCHAR}, #{displayName,jdbcType=VARCHAR},
      #{password,jdbcType=VARCHAR}, #{departmentCode,jdbcType=VARCHAR}, #{nimAccount,jdbcType=VARCHAR},
      #{nimToken,jdbcType=VARCHAR}, #{qsAccount,jdbcType=VARCHAR}, #{createTime,jdbcType=TIMESTAMP},
      #{updateTime,jdbcType=TIMESTAMP})
  </insert>
  <insert id="insertSelective" parameterType="com.hdsoft.model.User">
    <!--
      WARNING - @mbggenerated
      This element is automatically generated by MyBatis Generator, do not modify.
      This element was generated on Sat Jan 19 09:51:17 CST 2019.
    -->
    insert into coremailbridge_user
    <trim prefix="(" suffix=")" suffixOverrides=",">
      <if test="id != null">
        id,
      </if>
      <if test="userName != null">
        user_name,
      </if>
      <if test="displayName != null">
        display_name,
      </if>
      <if test="password != null">
        password,
      </if>
      <if test="departmentCode != null">
        department_code,
      </if>
      <if test="nimAccount != null">
        nim_account,
      </if>
      <if test="nimToken != null">
        nim_token,
      </if>
      <if test="qsAccount != null">
        qs_account,
      </if>
      <if test="createTime != null">
        create_time,
      </if>
      <if test="updateTime != null">
        update_time,
      </if>
    </trim>
    <trim prefix="values (" suffix=")" suffixOverrides=",">
      <if test="id != null">
        #{id,jdbcType=BIGINT},
      </if>
      <if test="userName != null">
        #{userName,jdbcType=VARCHAR},
      </if>
      <if test="displayName != null">
        #{displayName,jdbcType=VARCHAR},
      </if>
      <if test="password != null">
        #{password,jdbcType=VARCHAR},
      </if>
      <if test="departmentCode != null">
        #{departmentCode,jdbcType=VARCHAR},
      </if>
      <if test="nimAccount != null">
        #{nimAccount,jdbcType=VARCHAR},
      </if>
      <if test="nimToken != null">
        #{nimToken,jdbcType=VARCHAR},
      </if>
      <if test="qsAccount != null">
        #{qsAccount,jdbcType=VARCHAR},
      </if>
      <if test="createTime != null">
        #{createTime,jdbcType=TIMESTAMP},
      </if>
      <if test="updateTime != null">
        #{updateTime,jdbcType=TIMESTAMP},
      </if>
    </trim>
  </insert>
  <select id="countByExample" parameterType="com.hdsoft.model.UserExample" resultType="java.lang.Integer">
    <!--
      WARNING - @mbggenerated
      This element is automatically generated by MyBatis Generator, do not modify.
      This element was generated on Sat Jan 19 09:51:17 CST 2019.
    -->
    select count(*) from coremailbridge_user
    <if test="_parameter != null">
      <include refid="Example_Where_Clause" />
    </if>
  </select>
  <update id="updateByExampleSelective" parameterType="map">
    <!--
      WARNING - @mbggenerated
      This element is automatically generated by MyBatis Generator, do not modify.
      This element was generated on Sat Jan 19 09:51:17 CST 2019.
    -->
    update coremailbridge_user
    <set>
      <if test="record.id != null">
        id = #{record.id,jdbcType=BIGINT},
      </if>
      <if test="record.userName != null">
        user_name = #{record.userName,jdbcType=VARCHAR},
      </if>
      <if test="record.displayName != null">
        display_name = #{record.displayName,jdbcType=VARCHAR},
      </if>
      <if test="record.password != null">
        password = #{record.password,jdbcType=VARCHAR},
      </if>
      <if test="record.departmentCode != null">
        department_code = #{record.departmentCode,jdbcType=VARCHAR},
      </if>
      <if test="record.nimAccount != null">
        nim_account = #{record.nimAccount,jdbcType=VARCHAR},
      </if>
      <if test="record.nimToken != null">
        nim_token = #{record.nimToken,jdbcType=VARCHAR},
      </if>
      <if test="record.qsAccount != null">
        qs_account = #{record.qsAccount,jdbcType=VARCHAR},
      </if>
      <if test="record.createTime != null">
        create_time = #{record.createTime,jdbcType=TIMESTAMP},
      </if>
      <if test="record.updateTime != null">
        update_time = #{record.updateTime,jdbcType=TIMESTAMP},
      </if>
    </set>
    <if test="_parameter != null">
      <include refid="Update_By_Example_Where_Clause" />
    </if>
  </update>
  <update id="updateByExample" parameterType="map">
    <!--
      WARNING - @mbggenerated
      This element is automatically generated by MyBatis Generator, do not modify.
      This element was generated on Sat Jan 19 09:51:17 CST 2019.
    -->
    update coremailbridge_user
    set id = #{record.id,jdbcType=BIGINT},
      user_name = #{record.userName,jdbcType=VARCHAR},
      display_name = #{record.displayName,jdbcType=VARCHAR},
      password = #{record.password,jdbcType=VARCHAR},
      department_code = #{record.departmentCode,jdbcType=VARCHAR},
      nim_account = #{record.nimAccount,jdbcType=VARCHAR},
      nim_token = #{record.nimToken,jdbcType=VARCHAR},
      qs_account = #{record.qsAccount,jdbcType=VARCHAR},
      create_time = #{record.createTime,jdbcType=TIMESTAMP},
      update_time = #{record.updateTime,jdbcType=TIMESTAMP}
    <if test="_parameter != null">
      <include refid="Update_By_Example_Where_Clause" />
    </if>
  </update>
  <update id="updateByPrimaryKeySelective" parameterType="com.hdsoft.model.User">
    <!--
      WARNING - @mbggenerated
      This element is automatically generated by MyBatis Generator, do not modify.
      This element was generated on Sat Jan 19 09:51:17 CST 2019.
    -->
    update coremailbridge_user
    <set>
      <if test="userName != null">
        user_name = #{userName,jdbcType=VARCHAR},
      </if>
      <if test="displayName != null">
        display_name = #{displayName,jdbcType=VARCHAR},
      </if>
      <if test="password != null">
        password = #{password,jdbcType=VARCHAR},
      </if>
      <if test="departmentCode != null">
        department_code = #{departmentCode,jdbcType=VARCHAR},
      </if>
      <if test="nimAccount != null">
        nim_account = #{nimAccount,jdbcType=VARCHAR},
      </if>
      <if test="nimToken != null">
        nim_token = #{nimToken,jdbcType=VARCHAR},
      </if>
      <if test="qsAccount != null">
        qs_account = #{qsAccount,jdbcType=VARCHAR},
      </if>
      <if test="createTime != null">
        create_time = #{createTime,jdbcType=TIMESTAMP},
      </if>
      <if test="updateTime != null">
        update_time = #{updateTime,jdbcType=TIMESTAMP},
      </if>
    </set>
    where id = #{id,jdbcType=BIGINT}
  </update>
  <update id="updateByPrimaryKey" parameterType="com.hdsoft.model.User">
    <!--
      WARNING - @mbggenerated
      This element is automatically generated by MyBatis Generator, do not modify.
      This element was generated on Sat Jan 19 09:51:17 CST 2019.
    -->
    update coremailbridge_user
    set user_name = #{userName,jdbcType=VARCHAR},
      display_name = #{displayName,jdbcType=VARCHAR},
      password = #{password,jdbcType=VARCHAR},
      department_code = #{departmentCode,jdbcType=VARCHAR},
      nim_account = #{nimAccount,jdbcType=VARCHAR},
      nim_token = #{nimToken,jdbcType=VARCHAR},
      qs_account = #{qsAccount,jdbcType=VARCHAR},
      create_time = #{createTime,jdbcType=TIMESTAMP},
      update_time = #{updateTime,jdbcType=TIMESTAMP}
    where id = #{id,jdbcType=BIGINT}
  </update>
</mapper>
